{
  "name": "Samsøe Samsøe",
  "link": {
    "url": "https://www.samsoe.com/",
    "title": "samsoe.com"
  },
  "services": [
    "E-commerce",
    "Architecture",
    "Design",
    "Development",
    "Replatforming"
  ],
  "technologies": [
    "Centra",
    "Storyblok",
    "Aino Commerce Engine",
    "Voyado Elevate",
    "Voyado Engage"
  ],
  "reel": {
    "url": "/assets/work/samsoe-samsoe/samsoe.mp4",
    "width": 1920,
    "height": 1080
  },
  "sections": [
    {
      "className": "space"
    },
    {
      "className": "free between",
      "columns": [
        {
          "width": 8,
          "image": {
            "url": "/assets/work/samsoe-samsoe/samsoe_1.png",
            "width": 1920,
            "height": 1080
          }
        },
        {
          "className": "middle",
          "width": 3,
          "left": -2,
          "image": {
            "url": "/assets/work/samsoe-samsoe/samsoe_4.png",
            "width": 1920,
            "height": 1080
          }
        }
      ]
    },
    {
      "className": "space"
    },
    {
      "className": "free center",
      "columns": [
        {
          "width": 8,
          "image": {
            "url": "/assets/work/samsoe-samsoe/samsoe_5.png",
            "width": 1920,
            "height": 1080
          }
        }
      ]
    },
    {
      "className": "space"
    },
    {
      "className": "free margin between",
      "columns": [
        {
          "width": 4,
          "video": {
            "url": "/assets/work/samsoe-samsoe/cphfw.mp4",
            "width": 1800,
            "height": 2250
          }
        },
        {
          "width": 6,
          "image": {
            "url": "/assets/work/samsoe-samsoe/samsoe_6.png",
            "width": 1920,
            "height": 1080
          }
        }
      ]
    }
  ]
}
